{
    "Ar36": {
        "error": 0.0004501085704980259, 
        "fit": "Linear", 
        "value": 0.0326231578376742
    }, 
    "Ar37": {
        "error": 0.004529114685892644, 
        "fit": "linear", 
        "value": 0.09173316406155005
    }, 
    "Ar38": {
        "error": 0.011522902795444954, 
        "fit": "linear", 
        "value": 1.7293191151870175
    }, 
    "Ar39": {
        "error": 0.019904195876437197, 
        "fit": "Linear", 
        "value": 99.35009102186761
    }, 
    "Ar40": {
        "error": 0.1105985986195402, 
        "fit": "Linear", 
        "value": 2144.0888732713706
    }, 
    "Ar41": {
        "error": 0.005644686675669656, 
        "fit": "Average", 
        "value": 0.20668715399508208
    }
}