{
    "Ar36": {
        "error": 0.00041175370408949846, 
        "fit": "Linear", 
        "value": 0.023650126440870493
    }, 
    "Ar37": {
        "error": 0.004625573061652642, 
        "fit": "linear", 
        "value": 0.03240864087147011
    }, 
    "Ar38": {
        "error": 0.010273082700515627, 
        "fit": "linear", 
        "value": 0.20598956403315993
    }, 
    "Ar39": {
        "error": 0.01314557940604632, 
        "fit": "Linear", 
        "value": 1.244090881148209
    }, 
    "Ar40": {
        "error": 0.011062260099472435, 
        "fit": "Linear", 
        "value": 15.645457231186096
    }, 
    "Ar41": {
        "error": 0.005539944747199092, 
        "fit": "Average", 
        "value": 0.09785323980982244
    }
}